appr/__init__.py
appr/auth.py
appr/client.py
appr/config.py
appr/discovery.py
appr/display.py
appr/exception.py
appr/pack.py
appr/packager.py
appr/render_jsonnet.py
appr/semver.py
appr/template_filters.py
appr/utils.py
appr/api/__init__.py
appr/api/app.py
appr/api/builder.py
appr/api/config.py
appr/api/deployment.py
appr/api/gevent_app.py
appr/api/gunicorn_app.py
appr/api/info.py
appr/api/registry.py
appr/api/wsgi.py
appr/api/impl/__init__.py
appr/api/impl/builder.py
appr/api/impl/registry.py
appr/commands/__init__.py
appr/commands/channel.py
appr/commands/cli.py
appr/commands/command_base.py
appr/commands/config.py
appr/commands/delete_package.py
appr/commands/deploy.py
appr/commands/generate.py
appr/commands/helm.py
appr/commands/inspect.py
appr/commands/jsonnet.py
appr/commands/list_package.py
appr/commands/login.py
appr/commands/logout.py
appr/commands/plugins.py
appr/commands/pull.py
appr/commands/push.py
appr/commands/remove.py
appr/commands/runserver.py
appr/commands/show.py
appr/commands/version.py
appr/formats/__init__.py
appr/formats/base.py
appr/formats/convert.py
appr/formats/utils.py
appr/formats/appr/__init__.py
appr/formats/appr/appr_package.py
appr/formats/appr/kpm.py
appr/formats/appr/kub.py
appr/formats/appr/kub_base.py
appr/formats/appr/kubplain.py
appr/formats/appr/manifest.py
appr/formats/appr/manifest_jsonnet.py
appr/formats/helm/__init__.py
appr/formats/helm/chart.py
appr/formats/helm/manifest_chart.py
appr/jsonnet/manifest.jsonnet.j2
appr/jsonnet/lib/appr-native-ext.libsonnet
appr/jsonnet/lib/appr-utils.libsonnet
appr/jsonnet/lib/appr.libsonnet
appr/jsonnet/lib/kpm-utils.libjsonnet
appr/jsonnet/lib/kpm.libjsonnet
appr/models/__init__.py
appr/models/blob_base.py
appr/models/channel_base.py
appr/models/db_base.py
appr/models/package_base.py
appr/models/kv/__init__.py
appr/models/kv/blob_kv_base.py
appr/models/kv/channel_kv_base.py
appr/models/kv/models_index_base.py
appr-0.7.4.dist-info/DESCRIPTION.rst
appr-0.7.4.dist-info/METADATA
appr-0.7.4.dist-info/RECORD
appr-0.7.4.dist-info/WHEEL
appr-0.7.4.dist-info/dependency_links.txt
appr-0.7.4.dist-info/metadata.json
appr-0.7.4.dist-info/top_level.txt
