Metadata-Version: 2.0
Name: appr
Version: 0.7.4
Summary: cloud-native app registry server
Home-page: https://github.com/app-registry/appr-server
Author: Antoine Legrand
Author-email: 2t.antoine@gmail.com
License: Apache License version 2
Keywords: apprclient,apprclientpy,kubernetes
Platform: UNKNOWN
Classifier: Development Status :: 2 - Pre-Alpha
Classifier: Intended Audience :: Developers
Classifier: Natural Language :: English
Classifier: Programming Language :: Python :: 2
Classifier: Programming Language :: Python :: 2.7
Requires-Dist: Flask (>=0.10.1)
Requires-Dist: cryptography
Requires-Dist: ecdsa
Requires-Dist: flask
Requires-Dist: flask-cors
Requires-Dist: future
Requires-Dist: futures
Requires-Dist: gevent
Requires-Dist: gunicorn (>=19.7)
Requires-Dist: jinja2 (>=2.8)
Requires-Dist: jsonpatch
Requires-Dist: pathspec
Requires-Dist: pyopenssl
Requires-Dist: python-etcd
Requires-Dist: pyyaml
Requires-Dist: redis
Requires-Dist: requests
Requires-Dist: semantic-version
Requires-Dist: tabulate
Requires-Dist: tabulate
Requires-Dist: termcolor
Requires-Dist: urllib3 (<1.22)
Requires-Dist: urllib3[secure] (<1.22)
